notebooks/__init__.py
proforesight/__init__.py
tests/__init__.py
proforesight-0.0.1.dist-info/METADATA
proforesight-0.0.1.dist-info/WHEEL
proforesight-0.0.1.dist-info/top_level.txt
proforesight-0.0.1.dist-info/RECORD
