Metadata-Version: 2.1
Name: proforesight
Version: 0.0.1
Summary: Automation of the creation of a machine learning forecaster of company revenues
Home-page: https://github.com/Nil-Andreu/proforesight
Author: Nil Andreu
Author-email: nilandreug@email.com
License: MIT
Keywords: forecasting,forecast
Classifier: Development Status :: 3 - Alpha
Classifier: Intended Audience :: Developers
Classifier: Topic :: Software Development :: Build Tools
Classifier: License :: OSI Approved :: MIT License
Classifier: Programming Language :: Python :: 3.8
Classifier: Programming Language :: Python :: 3.9
Classifier: Programming Language :: Python :: 3.10
